MANIFEST.in
README.rst
__init__.py
setup.cfg
setup.py
django_msp_controldeacceso/__init__.py
django_msp_controldeacceso/__init__.pyc
django_msp_controldeacceso/config.pyc
django_msp_controldeacceso/forms.pyc
django_msp_controldeacceso/models.pyc
django_msp_controldeacceso/test_acceso.pyc
django_msp_controldeacceso/urls.pyc
django_msp_controldeacceso/views.pyc
django_msp_controldeacceso.egg-info/PKG-INFO
django_msp_controldeacceso.egg-info/SOURCES.txt
django_msp_controldeacceso.egg-info/dependency_links.txt
django_msp_controldeacceso.egg-info/top_level.txt
django_msp_controldeacceso/custom_db/__init__.py
django_msp_controldeacceso/custom_db/__init__.pyc
django_msp_controldeacceso/custom_db/procedures.pyc
django_msp_controldeacceso/templates/django_msp_controldeacceso/base.html
django_msp_controldeacceso/templates/django_msp_controldeacceso/cliente.html
django_msp_controldeacceso/templates/django_msp_controldeacceso/clientes.html
django_msp_controldeacceso/templates/django_msp_controldeacceso/imagen.html
django_msp_controldeacceso/templates/django_msp_controldeacceso/imagenes.html
django_msp_controldeacceso/templates/django_msp_controldeacceso/index.html
django_msp_controldeacceso/templates/django_msp_controldeacceso/log.html
django_msp_controldeacceso/templates/django_msp_controldeacceso/preferences.html
django_msp_controldeacceso/templates/django_msp_controldeacceso/search.html